any_case/__init__.py
any_case/contrib/__init__.py
any_case/contrib/django/__init__.py
any_case/contrib/django/middleware.py
any_case/contrib/django/parser.py
any_case/contrib/django/settings.py
any_case/contrib/django/utils.py
any_case/contrib/parser.py
any_case/contrib/rest_framework.py
any_case/converter.py
any_case-0.1.6.dist-info/LICENSE
any_case-0.1.6.dist-info/WHEEL
any_case-0.1.6.dist-info/METADATA
any_case-0.1.6.dist-info/RECORD
