Metadata-Version: 2.1
Name: any-case
Version: 0.1.6
Summary: Snake/Camel case converter with Django and Djnago REST framework integration
Home-page: https://github.com/asduj/any_case
License: MIT
Keywords: snake-case,django,rest_framework,camel-case
Author: asduj
Author-email: asduj@ya.ru
Requires-Python: >=3.6,<4.0
Classifier: License :: OSI Approved :: MIT License
Classifier: Programming Language :: Python :: 3
Classifier: Programming Language :: Python :: 3.6
Classifier: Programming Language :: Python :: 3.7
Project-URL: Repository, https://github.com/asduj/any_case
